pyrompt/__init__.py
pyrompt-0.0.4.dist-info/METADATA
pyrompt-0.0.4.dist-info/WHEEL
pyrompt-0.0.4.dist-info/licenses/LICENSE
pyrompt-0.0.4.dist-info/RECORD
