Metadata-Version: 2.4
Name: pyrompt
Version: 0.0.4
Summary: Managing & Operationalizing AI Prompts
Project-URL: Homepage, https://github.com/thorwhalen/pyrompt
License: mit
License-File: LICENSE
Requires-Python: >=3.8
